CHANGES.rst
MANIFEST.in
README.rst
message-extraction.ini
requirements-test.txt
requirements.txt
setup.cfg
setup.py
pyramid_sacrud/__init__.py
pyramid_sacrud/assets.py
pyramid_sacrud/common.py
pyramid_sacrud/exceptions.py
pyramid_sacrud/interfaces.py
pyramid_sacrud/resources.py
pyramid_sacrud/routes.py
pyramid_sacrud/views.py
pyramid_sacrud.egg-info/PKG-INFO
pyramid_sacrud.egg-info/SOURCES.txt
pyramid_sacrud.egg-info/dependency_links.txt
pyramid_sacrud.egg-info/not-zip-safe
pyramid_sacrud.egg-info/pbr.json
pyramid_sacrud.egg-info/requires.txt
pyramid_sacrud.egg-info/top_level.txt
pyramid_sacrud/locale/pyramid_sacrud.pot
pyramid_sacrud/locale/de/LC_MESSAGES/pyramid_sacrud.mo
pyramid_sacrud/locale/de/LC_MESSAGES/pyramid_sacrud.po
pyramid_sacrud/locale/ru/LC_MESSAGES/pyramid_sacrud.mo
pyramid_sacrud/locale/ru/LC_MESSAGES/pyramid_sacrud.po
pyramid_sacrud/localization/__init__.py
pyramid_sacrud/localization/views.py
pyramid_sacrud/static/css/__main.css
pyramid_sacrud/static/css/__main.css.map
pyramid_sacrud/static/css/main.scss
pyramid_sacrud/static/css/materialize.scss
pyramid_sacrud/static/css/breadcrumbs/main.scss
pyramid_sacrud/static/fonts/Material-Design-Icons.eot
pyramid_sacrud/static/fonts/Material-Design-Icons.ttf
pyramid_sacrud/static/fonts/Material-Design-Icons.woff
pyramid_sacrud/static/fonts/Material-Design-Icons.woff2
pyramid_sacrud/static/fonts/MaterialIcons-Regular.eot
pyramid_sacrud/static/fonts/MaterialIcons-Regular.ttf
pyramid_sacrud/static/fonts/MaterialIcons-Regular.woff
pyramid_sacrud/static/fonts/MaterialIcons-Regular.woff2
pyramid_sacrud/static/fonts/Roboto-Bold.eot
pyramid_sacrud/static/fonts/Roboto-Bold.ttf
pyramid_sacrud/static/fonts/Roboto-Bold.woff
pyramid_sacrud/static/fonts/Roboto-Bold.woff2
pyramid_sacrud/static/fonts/Roboto-Light.eot
pyramid_sacrud/static/fonts/Roboto-Light.ttf
pyramid_sacrud/static/fonts/Roboto-Light.woff
pyramid_sacrud/static/fonts/Roboto-Light.woff2
pyramid_sacrud/static/fonts/Roboto-Medium.eot
pyramid_sacrud/static/fonts/Roboto-Medium.ttf
pyramid_sacrud/static/fonts/Roboto-Medium.woff
pyramid_sacrud/static/fonts/Roboto-Medium.woff2
pyramid_sacrud/static/fonts/Roboto-Regular.eot
pyramid_sacrud/static/fonts/Roboto-Regular.ttf
pyramid_sacrud/static/fonts/Roboto-Regular.woff
