Metadata-Version: 1.1
Name: pyramid-sacrud
Version: 0.3.2
Summary: Pyramid CRUD, admin web interface.
Home-page: http://github.com/sacrud/pyramid_sacrud/
Author: Svintsov Dmitry
Author-email: sacrud@uralbash.ru
License: MIT
Platform: UNKNOWN
Classifier: Development Status :: 5 - Production/Stable
Classifier: Environment :: Console
Classifier: Environment :: Web Environment
Classifier: Intended Audience :: Developers
Classifier: License :: OSI Approved :: MIT License
Classifier: Natural Language :: English
Classifier: Natural Language :: Russian
Classifier: Operating System :: OS Independent
Classifier: Programming Language :: Python
Classifier: Programming Language :: Python :: 2.7
Classifier: Programming Language :: Python :: 3
Classifier: Programming Language :: Python :: 3.2
Classifier: Programming Language :: Python :: 3.3
Classifier: Programming Language :: Python :: 3.4
Classifier: Programming Language :: Python :: 3.5
Classifier: Framework :: Pyramid 
Classifier: Topic :: Internet
Classifier: Topic :: Database
